pygeoyandex.py
setup.py
pygeoyandex.egg-info/PKG-INFO
pygeoyandex.egg-info/SOURCES.txt
pygeoyandex.egg-info/dependency_links.txt
pygeoyandex.egg-info/top_level.txt