Metadata-Version: 1.0
Name: pygeoyandex
Version: 0.0.5
Summary: Yandex geocoding and reverse geocoding
Home-page: http://bitbucket.org/zakhar/pygeoyandex
Author: Zakhar Zibarov
Author-email: zakhar.zibarov@gmail.com
License: UNKNOWN
Platform: UNKNOWN
Classifier: Development Status :: 3 - Alpha
Classifier: Intended Audience :: Developers
Classifier: Programming Language :: Python
Classifier: Topic :: Software Development :: Libraries :: Python Modules
Classifier: Natural Language :: Russian
